{
  "observation": {
    "type": "Kinematics"
  },
  "action": {
    "type": "DiscreteMetaAction"
  },
  "simulation_frequency": 15,
  "policy_frequency": 1,
  "other_vehicles_type": "highway_env.vehicle.behavior.IDMVehicle",
  "screen_width": 600,
  "screen_height": 150,
  "centering_position": [
    0.3,
    0.5
  ],
  "scaling": 5.5,
  "show_trajectories": false,
  "render_agent": true,
  "offscreen_rendering": false,
  "manual_control": false,
  "real_time_rendering": false,
  "destination": null,
  "initial_vehicle_count": 0,
  "controlled_vehicles": 0,
  "spawn_probability": 0.0,
  "duration": 40.0,
  "collision_reward": -5,
  "high_speed_reward": 1.0,
  "arrived_reward": 1.0,
  "reward_speed_range": [
    6.0,
    12.0
  ],
  "auto_curve": false,
  "corner_radius": 25.0,
  "curve_samples": 8,
  "exit_distance": 5.0,
  "graph": {
    "nodes": {
      "366381056": [
        204.17059,
        282.32295
      ],
      "5168393218": [
        843.8632,
        941.8017
      ],
      "5168393219": [
        866.97211,
        702.8076
      ],
      "5168393220": [
        867.16887,
        699.9993
      ],
      "5168393221": [
        876.85406,
        618.6141
      ],
      "5168393222": [
        880.07335,
        581.7954
      ],
      "2153156619": [
        622.37186,
        434.32635
      ],
      "366466060": [
        166.8673,
        193.57845
      ],
      "366385675": [
        161.78422,
        165.73965
      ],
      "366384660": [
        926.77215,
        475.92915
      ],
      "2153156635": [
        765.44158,
        456.6207
      ],
      "366434338": [
        784.29272,
        458.66865
      ],
      "1628403235": [
        745.55742,
        1102.01355
      ],
      "2153156644": [
        892.00494,
        471.46695
      ],
      "2153156645": [
        903.09481,
        473.04315
      ],
      "366397480": [
        135.09529,
        44.98275
      ],
      "2351816153": [
        843.48607,
        950.45415
      ],
      "366452782": [
        647.30631,
        440.9919
      ],
      "5811478574": [
        176.60715,
        239.5047
      ],
      "366431281": [
        399.76006,
        380.12505
      ],
      "2159584309": [
        832.74053,
        464.71815
      ],
      "2351816155": [
        774.0555,
        1064.81745
      ],
      "366369341": [
        240.45179,
        304.7172
      ],
      "5811478590": [
        194.20118,
        273.2598
      ],
      "5811478589": [
        189.51163,
        268.287
      ],
      "5811478591": [
        175.58507,
        234.6429
      ],
      "5811478597": [
        169.44711,
        204.68955
      ],
      "5811348553": [
        60.50511,
        79.73685
      ],
      "5811348554": [
        114.27104,
        3.3855
      ],
      "5811348555": [
        121.4912,
        1.88145
      ],
      "5811478618": [
        8.49367,
        209.8011
      ],
      "2159584348": [
        860.69204,
        468.0204
      ],
      "366461023": [
        178.25232,
        245.03805
      ],
      "2346953828": [
        832.31421,
        961.94265
      ],
      "366435947": [
        182.4281,
        256.53765
      ],
      "366466668": [
        187.12859,
        264.69615
      ],
      "2159584370": [
        1085.65955,
        495.04335
      ],
      "2341518964": [
        838.88943,
        954.2226
      ],
      "2341518966": [
        811.81243,
        985.57455
      ],
      "5811821179": [
        847.12621,
        908.08545
      ],
      "5811821180": [
        848.61288,
        892.70085
      ],
      "5811821181": [
        855.9205,
        817.3707
      ],
      "5811821182": [
        854.13322,
        835.6191
      ],
      "5811664513": [
        233.08405,
        299.91645
      ],
      "5811677825": [
        1004.12796,
        484.93125
      ],
      "5811677842": [
        897.44876,
        472.3272
      ],
      "366416019": [
        155.4003,
        138.1062
      ],
      "5811677845": [
        911.4573,
        474.06435
      ],
      "366442152": [
        364.07461,
        374.86365
      ],
      "366383786": [
        575.20848,
        419.31915
      ],
      "366433970": [
        144.74768,
        91.82475
      ],
      "366432948": [
        325.39944,
        354.3564
      ],
      "5811875291": [
        789.52338,
        1029.5361
      ],
      "5811875292": [
        834.91041,
        951.2589
      ],
      "5598941893": [
        235.5764,
        301.52595
      ],
      "366384838": [
        275.36658,
        324.7749
      ],
      "366426823": [
        710.21632,
        450.2604
      ],
      "366381783": [
        1029.01868,
        487.75065
      ],
      "2351814879": [
        778.81611,
        1057.1085
      ],
      "2351814881": [
        851.39491,
        944.60445
      ],
      "2351814884": [
        774.83162,
        1054.64985
      ],
      "366397697": [
        664.14061,
        443.9556
      ],
      "366477092": [
        392.57268,
        380.0418
      ],
      "5811493705": [
        827.82142,
        969.54615
      ],
      "5811493706": [
        824.21407,
        964.62885
      ],
      "5811493707": [
        832.06279,
        968.78025
      ],
      "5811493708": [
        835.07438,
        958.33515
      ],
      "5811493709": [
        826.01228,
        972.19905
      ],
      "5811493710": [
        830.48867,
        972.7152
      ],
      "5811493711": [
        822.27922,
        966.42705
      ],
      "5811493712": [
        782.85525,
        1048.0842
      ],
      "5811493713": [
        814.79123,
        1001.82495
      ],
      "5811493714": [
        810.80128,
        999.7659
      ],
      "5811493715": [
        804.09489,
        997.9677
      ],
      "5811493716": [
        786.01988,
        1026.97755
      ],
      "5811493717": [
        791.74245,
        1031.5452
      ],
      "5811493718": [
        795.99475,
        1034.25915
      ],
      "5811493720": [
        781.63093,
        1059.1731
      ],
      "5811493721": [
        771.61234,
        1075.1016
      ],
      "5811493722": [
        770.80888,
        1051.39755
      ],
      "5811493723": [
        741.31605,
        1098.96105
      ],
      "2244906852": [
        768.8303,
        1073.9361
      ],
      "366475621": [
        476.70594,
        376.4343
      ],
      "366422373": [
        375.39951,
        378.37125
      ],
      "366416234": [
        816.85179,
        462.84225
      ],
      "714567022": [
        97.01587,
        50.2164
      ],
      "366381940": [
        445.50782,
        373.86465
      ],
      "714567031": [
        976.75035,
        481.8288
      ],
      "2244906876": [
        821.08223,
        990.72495
      ],
      "5811547518": [
        369.9065,
        377.26125
      ],
      "714567039": [
        674.29585,
        444.7881
      ],
      "5811547520": [
        384.56546,
        379.89195
      ],
      "5811615621": [
        246.66628,
        308.2914
      ],
      "714567046": [
        89.48963,
        0.0
      ],
      "714567051": [
        111.47261,
        5.6166
      ],
      "2153156495": [
        77.04427,
        42.51855
      ],
      "714567058": [
        15.927,
        199.5003
      ],
      "5811547540": [
        315.70878,
        348.6288
      ],
      "714567061": [
        0.0,
        185.6142
      ],
      "5811347350": [
        52.43776,
        96.99735
      ],
      "5811347351": [
        24.43707,
        150.24405
      ],
      "5811347352": [
        39.8339,
        165.3123
      ],
      "714567067": [
        124.38255,
        3.7962
      ],
      "714567077": [
        91.42995,
        64.0026
      ],
      "714567090": [
        604.89807,
        428.84295
      ],
      "714567092": [
        102.90788,
        33.70515
      ],
      "5811477942": [
        190.93271,
        269.7966
      ],
      "714567094": [
        172.97247,
        219.8577
      ],
      "366447546": [
        741.84076,
        454.767
      ],
      "714567102": [
        43.40845,
        115.0293
      ],
      "714567106": [
        117.73628,
        1.8648
      ],
      "5811875272": [
        838.65987,
        948.5172
      ],
      "714567117": [
        61.02435,
        127.78875
      ],
      "2153156564": [
        347.64477,
        367.3212
      ],
      "714567126": [
        128.28505,
        11.1111
      ],
      "2153156568": [
        456.47745,
        373.5039
      ],
      "5811875289": [
        856.15552,
        949.26645
      ],
      "2153156570": [
        422.74325,
        376.401
      ],
      "1628403162": [
        858.18329,
        945.4869
      ],
      "2153156572": [
        412.1289,
        377.58315
      ],
      "1628403164": [
        850.99045,
        949.09995
      ],
      "1628403165": [
        887.7745,
        952.89615
      ],
      "2351816154": [
        770.59572,
        1061.55405
      ],
      "5811875296": [
        843.42595,
        946.0863
      ],
      "5811875297": [
        853.94739,
        944.5434
      ],
      "5811875290": [
        807.7405,
        998.889
      ],
      "1628403171": [
        886.70869,
        958.04655
      ],
      "5811875295": [
        824.9574,
        967.3206
      ],
      "5811875294": [
        827.70664,
        962.0148
      ],
      "5811875293": [
        831.06257,
        956.3316
      ],
      "5811875304": [
        844.08729,
        939.46515
      ],
      "1628403181": [
        996.21365,
        983.69865
      ],
      "366384110": [
        878.94742,
        470.1738
      ],
      "1628403183": [
        1043.95092,
        989.7426
      ],
      "5811875312": [
        886.85626,
        470.75655
      ],
      "1628403184": [
        1042.60637,
        994.87635
      ],
      "1628403185": [
        1083.42409,
        998.7447
      ],
      "5811763199": [
        849.0228,
        888.5106
      ]
    },
    "edges": [
      {
        "start": "366461023",
        "end": "366461023",
        "reverse": false,
        "shape": {
          "type": "polyline",
          "points": [
            [
              178.25232,
              245.03805
            ],
            [
              182.4281,
              256.53765
            ],
            [
              178.25232,
              245.03805
            ]
          ]
        },
        "metadata": {
          "segment_id": 20054,
          "street_id": 33569362,
          "street_name": "Ph\u1ea1m H\u1eefu L\u1ea7u",
          "street_type": "tertiary",
          "street_level": 4,
          "street_group": "33569362",
          "composite": true
        },
        "length_hint": 24.468587108241437,
        "speed_limit": 13.88888888888889
      },
      {
        "start": "366461023",
        "end": "366461023",
        "reverse": false,
        "shape": {
          "type": "polyline",
          "points": [
            [
              178.25232,
              245.03805
            ],
            [
              176.60715,
              239.5047
            ],
            [
              178.25232,
              245.03805
            ]
          ]
        },
        "metadata": {
          "segment_id": 20055,
          "street_id": 33569362,
          "street_name": "Ph\u1ea1m H\u1eefu L\u1ea7u",
          "street_type": "tertiary",
          "street_level": 4,
          "street_group": "33569362",
          "composite": true
        },
        "length_hint": 11.545483368209378,
        "speed_limit": 13.88888888888889
      },
      {
        "start": "5811478574",
        "end": "5811478574",
        "reverse": false,
        "shape": {
          "type": "polyline",
          "points": [
            [
              176.60715,
              239.5047
            ],
            [
              175.58507,
              234.6429
            ],
            [
              176.60715,
              239.5047
            ]
          ]
        },
        "metadata": {
          "segment_id": 20057,
          "street_id": 33569362,
          "street_name": "Ph\u1ea1m H\u1eefu L\u1ea7u",
          "street_type": "tertiary",
          "street_level": 4,
          "street_group": "33569362",
          "composite": true
        },
        "length_hint": 9.936145483314974,
        "speed_limit": 13.88888888888889
      },
      {
        "start": "366397480",
        "end": "366397480",
        "reverse": false,
        "shape": {
          "type": "polyline",
          "points": [
            [
              135.09529,
              44.98275
            ],
            [
              144.74768,
              91.82475
            ],
            [
              135.09529,
              44.98275
            ]
          ]
        },
        "metadata": {
          "segment_id": 20072,
          "street_id": 33569362,
          "street_name": "Ph\u1ea1m H\u1eefu L\u1ea7u",
          "street_type": "tertiary",
          "street_level": 4,
          "street_group": "33569362",
          "composite": true
        },
        "length_hint": 95.6523203422081,
        "speed_limit": 13.88888888888889
      },
      {
        "start": "366397480",
        "end": "366397480",
        "reverse": false,
        "shape": {
          "type": "polyline",
          "points": [
            [
              135.09529,
              44.98275
            ],
            [
              128.28505,
              11.1111
            ],
            [
              135.09529,
              44.98275
            ]
          ]
        },
        "metadata": {
          "segment_id": 20073,
          "street_id": 33569362,
          "street_name": "Ph\u1ea1m H\u1eefu L\u1ea7u",
          "street_type": "tertiary",
          "street_level": 4,
          "street_group": "33569362",
          "composite": true
        },
        "length_hint": 69.09900267240042,
        "speed_limit": 13.88888888888889
      },
      {
        "start": "366433970",
        "end": "366433970",
        "reverse": false,
        "shape": {
          "type": "polyline",
          "points": [
            [
              144.74768,
              91.82475
            ],
            [
              155.4003,
              138.1062
            ],
            [
              144.74768,
              91.82475
            ]
          ]
        },
        "metadata": {
          "segment_id": 20070,
          "street_id": 33569362,
          "street_name": "Ph\u1ea1m H\u1eefu L\u1ea7u",
          "street_type": "tertiary",
          "street_level": 4,
          "street_group": "33569362",
          "composite": true
        },
        "length_hint": 94.98317592009441,
        "speed_limit": 13.88888888888889
      },
      {
        "start": "366416019",
        "end": "366416019",
        "reverse": false,
        "shape": {
          "type": "polyline",
          "points": [
            [
              155.4003,
              138.1062
            ],
            [
              161.78422,
              165.73965
            ],
            [
              155.4003,
              138.1062
            ]
          ]
        },
        "metadata": {
          "segment_id": 20068,
          "street_id": 33569362,
          "street_name": "Ph\u1ea1m H\u1eefu L\u1ea7u",
          "street_type": "tertiary",
          "street_level": 4,
          "street_group": "33569362",
          "composite": true
        },
        "length_hint": 56.722552603665534,
        "speed_limit": 13.88888888888889
      },
      {
        "start": "5811478591",
        "end": "5811478591",
        "reverse": false,
        "shape": {
          "type": "polyline",
          "points": [
            [
              175.58507,
              234.6429
            ],
            [
              172.97247,
              219.8577
            ],
            [
              175.58507,
              234.6429
            ]
          ]
        },
        "metadata": {
          "segment_id": 20059,
          "street_id": 33569362,
          "street_name": "Ph\u1ea1m H\u1eefu L\u1ea7u",
          "street_type": "tertiary",
          "street_level": 4,
          "street_group": "33569362",
          "composite": true
        },
        "length_hint": 30.028507641905893,
        "speed_limit": 13.88888888888889
      },
      {
        "start": "366385675",
        "end": "366385675",
        "reverse": false,
        "shape": {
          "type": "polyline",
          "points": [
            [
              161.78422,
              165.73965
            ],
            [
              166.8673,
              193.57845
            ],
            [
              161.78422,
              165.73965
            ]
          ]
        },
        "metadata": {
          "segment_id": 20066,
          "street_id": 33569362,
          "street_name": "Ph\u1ea1m H\u1eefu L\u1ea7u",
          "street_type": "tertiary",
          "street_level": 4,
          "street_group": "33569362",
          "composite": true
        },
        "length_hint": 56.59810907535337,
        "speed_limit": 13.88888888888889
      },
      {
        "start": "5811478597",
        "end": "5811478597",
        "reverse": false,
        "shape": {
          "type": "polyline",
          "points": [
            [
              169.44711,
              204.68955
            ],
            [
              172.97247,
              219.8577
            ],
            [
              169.44711,
              204.68955
            ]
          ]
        },
        "metadata": {
          "segment_id": 20062,
          "street_id": 33569362,
          "street_name": "Ph\u1ea1m H\u1eefu L\u1ea7u",
          "street_type": "tertiary",
          "street_level": 4,
          "street_group": "33569362",
          "composite": true
        },
        "length_hint": 31.144883210704116,
        "speed_limit": 13.88888888888889
      },
      {
        "start": "5811478597",
        "end": "5811478597",
        "reverse": false,
        "shape": {
          "type": "polyline",
          "points": [
            [
              169.44711,
              204.68955
            ],
            [
              166.8673,
              193.57845
            ],
            [
              169.44711,
              204.68955
            ]
          ]
        },
        "metadata": {
          "segment_id": 20063,
          "street_id": 33569362,
          "street_name": "Ph\u1ea1m H\u1eefu L\u1ea7u",
          "street_type": "tertiary",
          "street_level": 4,
          "street_group": "33569362",
          "composite": true
        },
        "length_hint": 22.81332617976606,
        "speed_limit": 13.88888888888889
      },
      {
        "start": "366384838",
        "end": "366384838",
        "reverse": false,
        "shape": {
          "type": "polyline",
          "points": [
            [
              275.36658,
              324.7749
            ],
            [
              315.70878,
              348.6288
            ],
            [
              275.36658,
              324.7749
            ]
          ]
        },
        "metadata": {
          "segment_id": 20032,
          "street_id": 33569362,
          "street_name": "Ph\u1ea1m H\u1eefu L\u1ea7u",
          "street_type": "tertiary",
          "street_level": 4,
          "street_group": "33569362",
          "composite": true
        },
        "length_hint": 93.7337003654502,
        "speed_limit": 13.88888888888889
      },
      {
        "start": "366384838",
        "end": "366384838",
        "reverse": false,
        "shape": {
          "type": "polyline",
          "points": [
            [
              275.36658,
              324.7749
            ],
            [
              246.66628,
              308.2914
            ],
            [
              275.36658,
              324.7749
            ]
          ]
        },
        "metadata": {
          "segment_id": 20033,
          "street_id": 33569362,
          "street_name": "Ph\u1ea1m H\u1eefu L\u1ea7u",
          "street_type": "tertiary",
          "street_level": 4,
          "street_group": "33569362",
          "composite": true
        },
        "length_hint": 66.19404783936392,
        "speed_limit": 13.88888888888889
      },
      {
        "start": "2153156570",
        "end": "2153156570",
        "reverse": false,
        "shape": {
          "type": "polyline",
          "points": [
            [
              422.74325,
              376.401
            ],
            [
              445.50782,
              373.86465
            ],
            [
              422.74325,
              376.401
            ]
          ]
        },
        "metadata": {
          "segment_id": 20010,
          "street_id": 33569362,
          "street_name": "Ph\u1ea1m H\u1eefu L\u1ea7u",
          "street_type": "tertiary",
          "street_level": 4,
          "street_group": "33569362",
          "composite": true
        },
        "length_hint": 45.810859787059215,
        "speed_limit": 13.88888888888889
      },
      {
        "start": "2153156570",
        "end": "2153156570",
        "reverse": false,
        "shape": {
          "type": "polyline",
          "points": [
            [
              422.74325,
              376.401
            ],
            [
              412.1289,
              377.58315
            ],
            [
              422.74325,
              376.401
            ]
          ]
        },
        "metadata": {
          "segment_id": 20011,
          "street_id": 33569362,
          "street_name": "Ph\u1ea1m H\u1eefu L\u1ea7u",
          "street_type": "tertiary",
          "street_level": 4,
          "street_group": "33569362",
          "composite": true
        },
        "length_hint": 21.35995360903202,
        "speed_limit": 13.88888888888889
      },
      {
        "start": "366475621",
        "end": "366475621",
        "reverse": false,
        "shape": {
          "type": "polyline",
          "points": [
            [
              476.70594,
              376.4343
            ],
            [
              456.47745,
              373.5039
            ],
            [
              476.70594,
              376.4343
            ]
          ]
        },
        "metadata": {
          "segment_id": 20005,
          "street_id": 33569362,
          "street_name": "Ph\u1ea1m H\u1eefu L\u1ea7u",
          "street_type": "tertiary",
          "street_level": 4,
          "street_group": "33569362",
          "composite": true
        },
        "length_hint": 40.879288244298046,
        "speed_limit": 13.88888888888889
      },
      {
        "start": "2153156568",
        "end": "2153156568",
        "reverse": false,
        "shape": {
          "type": "polyline",
          "points": [
            [
              456.47745,
              373.5039
            ],
            [
              445.50782,
              373.86465
            ],
            [
              456.47745,
              373.5039
            ]
          ]
        },
        "metadata": {
          "segment_id": 20007,
          "street_id": 33569362,
          "street_name": "Ph\u1ea1m H\u1eefu L\u1ea7u",
          "street_type": "tertiary",
          "street_level": 4,
          "street_group": "33569362",
          "composite": true
        },
        "length_hint": 21.951120508930735,
        "speed_limit": 13.88888888888889
      },
      {
        "start": "366477092",
        "end": "366477092",
        "reverse": false,
        "shape": {
          "type": "polyline",
          "points": [
            [
              392.57268,
              380.0418
            ],
            [
              399.76006,
              380.12505
            ],
            [
              392.57268,
              380.0418
            ]
          ]
        },
        "metadata": {
          "segment_id": 20016,
          "street_id": 33569362,
          "street_name": "Ph\u1ea1m H\u1eefu L\u1ea7u",
          "street_type": "tertiary",
          "street_level": 4,
          "street_group": "33569362",
          "composite": true
        },
        "length_hint": 14.375724235933335,
        "speed_limit": 13.88888888888889
      },
      {
        "start": "366477092",
        "end": "366477092",
        "reverse": false,
        "shape": {
          "type": "polyline",
          "points": [
            [
              392.57268,
              380.0418
            ],
            [
              384.56546,
              379.89195
            ],
            [
              392.57268,
              380.0418
            ]
          ]
        },
        "metadata": {
          "segment_id": 20017,
          "street_id": 33569362,
          "street_name": "Ph\u1ea1m H\u1eefu L\u1ea7u",
          "street_type": "tertiary",
          "street_level": 4,
          "street_group": "33569362",
          "composite": true
        },
        "length_hint": 16.017244101392762,
        "speed_limit": 13.88888888888889
      },
      {
        "start": "366432948",
        "end": "366432948",
        "reverse": false,
        "shape": {
          "type": "polyline",
          "points": [
            [
              325.39944,
              354.3564
            ],
            [
              347.64477,
              367.3212
            ],
            [
              325.39944,
              354.3564
            ]
          ]
        },
        "metadata": {
          "segment_id": 20028,
          "street_id": 33569362,
          "street_name": "Ph\u1ea1m H\u1eefu L\u1ea7u",
          "street_type": "tertiary",
          "street_level": 4,
          "street_group": "33569362",
          "composite": true
        },
        "length_hint": 51.495271466374376,
        "speed_limit": 13.88888888888889
      },
      {
        "start": "366432948",
        "end": "366432948",
        "reverse": false,
        "shape": {
          "type": "polyline",
          "points": [
            [
              325.39944,
              354.3564
            ],
            [
              315.70878,
              348.6288
            ],
            [
              325.39944,
              354.3564
            ]
          ]
        },
        "metadata": {
          "segment_id": 20029,
          "street_id": 33569362,
          "street_name": "Ph\u1ea1m H\u1eefu L\u1ea7u",
          "street_type": "tertiary",
          "street_level": 4,
          "street_group": "33569362",
          "composite": true
        },
        "length_hint": 22.513488667516693,
        "speed_limit": 13.88888888888889
      },
      {
        "start": "5811547518",
        "end": "5811547518",
        "reverse": false,
        "shape": {
          "type": "polyline",
          "points": [
            [
              369.9065,
              377.26125
            ],
            [
              375.39951,
              378.37125
            ],
            [
              369.9065,
              377.26125
            ]
          ]
        },
        "metadata": {
          "segment_id": 20022,
          "street_id": 33569362,
          "street_name": "Ph\u1ea1m H\u1eefu L\u1ea7u",
          "street_type": "tertiary",
          "street_level": 4,
          "street_group": "33569362",
          "composite": true
        },
        "length_hint": 11.208079025435215,
        "speed_limit": 13.88888888888889
      },
      {
        "start": "5811547518",
        "end": "5811547518",
        "reverse": false,
        "shape": {
          "type": "polyline",
          "points": [
            [
              369.9065,
              377.26125
            ],
            [
              364.07461,
              374.86365
            ],
            [
              369.9065,
              377.26125
            ]
          ]
        },
        "metadata": {
          "segment_id": 20023,
          "street_id": 33569362,
          "street_name": "Ph\u1ea1m H\u1eefu L\u1ea7u",
          "street_type": "tertiary",
          "street_level": 4,
          "street_group": "33569362",
          "composite": true
        },
        "length_hint": 12.611015301251507,
        "speed_limit": 13.88888888888889
      },
      {
        "start": "366442152",
        "end": "366442152",
        "reverse": false,
        "shape": {
          "type": "polyline",
          "points": [
            [
              364.07461,
              374.86365
            ],
            [
              347.64477,
              367.3212
            ],
            [
              364.07461,
              374.86365
            ]
          ]
        },
        "metadata": {
          "segment_id": 20025,
          "street_id": 33569362,
          "street_name": "Ph\u1ea1m H\u1eefu L\u1ea7u",
          "street_type": "tertiary",
          "street_level": 4,
          "street_group": "33569362",
          "composite": true
        },
        "length_hint": 36.15678052194918,
        "speed_limit": 13.88888888888889
      },
      {
        "start": "366422373",
        "end": "366422373",
        "reverse": false,
        "shape": {
          "type": "polyline",
          "points": [
            [
              375.39951,
              378.37125
            ],
            [
              384.56546,
              379.89195
            ],
            [
              375.39951,
              378.37125
            ]
          ]
        },
        "metadata": {
          "segment_id": 20020,
          "street_id": 33569362,
          "street_name": "Ph\u1ea1m H\u1eefu L\u1ea7u",
          "street_type": "tertiary",
          "street_level": 4,
          "street_group": "33569362",
          "composite": true
        },
        "length_hint": 18.58248292263434,
        "speed_limit": 13.88888888888889
      },
      {
        "start": "366431281",
        "end": "366431281",
        "reverse": false,
        "shape": {
          "type": "polyline",
          "points": [
            [
              399.76006,
              380.12505
            ],
            [
              412.1289,
              377.58315
            ],
            [
              399.76006,
              380.12505
            ]
          ]
        },
        "metadata": {
          "segment_id": 20014,
          "street_id": 33569362,
          "street_name": "Ph\u1ea1m H\u1eefu L\u1ea7u",
          "street_type": "tertiary",
          "street_level": 4,
          "street_group": "33569362",
          "composite": true
        },
        "length_hint": 25.25465965366387,
        "speed_limit": 13.88888888888889
      },
      {
        "start": "5811477942",
        "end": "5811477942",
        "reverse": false,
        "shape": {
          "type": "polyline",
          "points": [
            [
              190.93271,
              269.7966
            ],
            [
              194.20118,
              273.2598
            ],
            [
              190.93271,
              269.7966
            ]
          ]
        },
        "metadata": {
          "segment_id": 20046,
          "street_id": 33569362,
          "street_name": "Ph\u1ea1m H\u1eefu L\u1ea7u",
          "street_type": "tertiary",
          "street_level": 4,
          "street_group": "33569362",
          "composite": true
        },
        "length_hint": 9.524001339962076,
        "speed_limit": 13.88888888888889
      },
      {
        "start": "5811477942",
        "end": "5811477942",
        "reverse": false,
        "shape": {
          "type": "polyline",
          "points": [
            [
              190.93271,
              269.7966
            ],
            [
              189.51163,
              268.287
            ],
            [
              190.93271,
              269.7966
            ]
          ]
        },
        "metadata": {
          "segment_id": 20047,
          "street_id": 33569362,
          "street_name": "Ph\u1ea1m H\u1eefu L\u1ea7u",
          "street_type": "tertiary",
          "street_level": 4,
          "street_group": "33569362",
          "composite": true
        },
        "length_hint": 4.146497570914554,
        "speed_limit": 13.88888888888889
      },
      {
        "start": "366381056",
        "end": "366381056",
        "reverse": false,
        "shape": {
          "type": "polyline",
          "points": [
            [
              204.17059,
              282.32295
            ],
            [
              233.08405,
              299.91645
            ],
            [
              204.17059,
              282.32295
            ]
          ]
        },
        "metadata": {
          "segment_id": 20042,
          "street_id": 33569362,
          "street_name": "Ph\u1ea1m H\u1eefu L\u1ea7u",
          "street_type": "tertiary",
          "street_level": 4,
          "street_group": "33569362",
          "composite": true
        },
        "length_hint": 67.69104553547979,
        "speed_limit": 13.88888888888889
      },
      {
        "start": "366381056",
        "end": "366381056",
        "reverse": false,
        "shape": {
          "type": "polyline",
          "points": [
            [
              204.17059,
              282.32295
            ],
            [
              194.20118,
              273.2598
            ],
            [
              204.17059,
              282.32295
            ]
          ]
        },
        "metadata": {
          "segment_id": 20043,
          "street_id": 33569362,
          "street_name": "Ph\u1ea1m H\u1eefu L\u1ea7u",
          "street_type": "tertiary",
          "street_level": 4,
          "street_group": "33569362",
          "composite": true
        },
        "length_hint": 26.94660080014549,
        "speed_limit": 13.88888888888889
      },
      {
        "start": "5811615621",
        "end": "5811615621",
        "reverse": false,
        "shape": {
          "type": "polyline",
          "points": [
            [
              246.66628,
              308.2914
            ],
            [
              240.45179,
              304.7172
            ],
            [
              246.66628,
              308.2914
            ]
          ]
        },
        "metadata": {
          "segment_id": 20035,
          "street_id": 33569362,
          "street_name": "Ph\u1ea1m H\u1eefu L\u1ea7u",
          "street_type": "tertiary",
          "street_level": 4,
          "street_group": "33569362",
          "composite": true
        },
        "length_hint": 14.338032166249354,
        "speed_limit": 13.88888888888889
      },
      {
        "start": "366369341",
        "end": "366369341",
        "reverse": false,
        "shape": {
          "type": "polyline",
          "points": [
            [
              240.45179,
              304.7172
            ],
            [
              235.5764,
              301.52595
            ],
            [
              240.45179,
              304.7172
            ]
          ]
        },
        "metadata": {
          "segment_id": 20037,
          "street_id": 33569362,
          "street_name": "Ph\u1ea1m H\u1eefu L\u1ea7u",
          "street_type": "tertiary",
          "street_level": 4,
          "street_group": "33569362",
          "composite": true
        },
        "length_hint": 11.65392710026961,
        "speed_limit": 13.88888888888889
      },
      {
        "start": "5811664513",
        "end": "5811664513",
        "reverse": false,
        "shape": {
          "type": "polyline",
          "points": [
            [
              233.08405,
              299.91645
            ],
            [
              235.5764,
              301.52595
            ],
            [
              233.08405,
              299.91645
            ]
          ]
        },
        "metadata": {
          "segment_id": 20040,
          "street_id": 33569362,
          "street_name": "Ph\u1ea1m H\u1eefu L\u1ea7u",
          "street_type": "tertiary",
          "street_level": 4,
          "street_group": "33569362",
          "composite": true
        },
        "length_hint": 5.933733655128164,
        "speed_limit": 13.88888888888889
      },
      {
        "start": "366466668",
        "end": "366466668",
        "reverse": false,
        "shape": {
          "type": "polyline",
          "points": [
            [
              187.12859,
              264.69615
            ],
            [
              189.51163,
              268.287
            ],
            [
              187.12859,
              264.69615
            ]
          ]
        },
        "metadata": {
          "segment_id": 20050,
          "street_id": 33569362,
          "street_name": "Ph\u1ea1m H\u1eefu L\u1ea7u",
          "street_type": "tertiary",
          "street_level": 4,
          "street_group": "33569362",
          "composite": true
        },
        "length_hint": 8.619300056060212,
        "speed_limit": 13.88888888888889
      },
      {
        "start": "366466668",
        "end": "366466668",
        "reverse": false,
        "shape": {
          "type": "polyline",
          "points": [
            [
              187.12859,
              264.69615
            ],
            [
              182.4281,
              256.53765
            ],
            [
              187.12859,
              264.69615
            ]
          ]
        },
        "metadata": {
          "segment_id": 20051,
          "street_id": 33569362,
          "street_name": "Ph\u1ea1m H\u1eefu L\u1ea7u",
          "street_type": "tertiary",
          "street_level": 4,
          "street_group": "33569362",
          "composite": true
        },
        "length_hint": 18.831434198180453,
        "speed_limit": 13.88888888888889
      },
      {
        "start": "5811875296",
        "end": "5811875296",
        "reverse": false,
        "shape": {
          "type": "polyline",
          "points": [
            [
              843.42595,
              946.0863
            ],
            [
              843.48607,
              950.45415
            ],
            [
              843.42595,
              946.0863
            ]
          ]
        },
        "metadata": {
          "segment_id": 83352,
          "street_id": 614395972,
          "street_name": "Nguy\u1ec5n L\u01b0\u01a1ng B\u1eb1ng n\u1ed1i d\u00e0i",
          "street_type": "tertiary",
          "street_level": 4,
          "street_group": "614395972",
          "composite": true
        },
        "length_hint": 8.7365274650515,
        "speed_limit": 13.88888888888889
      },
      {
        "start": "5811875296",
        "end": "5811875296",
        "reverse": false,
        "shape": {
          "type": "polyline",
          "points": [
            [
              843.42595,
              946.0863
            ],
            [
              843.8632,
              941.8017
            ],
            [
              843.42595,
              946.0863
            ]
          ]
        },
        "metadata": {
          "segment_id": 83353,
          "street_id": 614395972,
          "street_name": "Nguy\u1ec5n L\u01b0\u01a1ng B\u1eb1ng n\u1ed1i d\u00e0i",
          "street_type": "tertiary",
          "street_level": 4,
          "street_group": "614395972",
          "composite": true
        },
        "length_hint": 8.61370645483131,
        "speed_limit": 13.88888888888889
      },
      {
        "start": "5168393218",
        "end": "5168393218",
        "reverse": false,
        "shape": {
          "type": "polyline",
          "points": [
            [
              843.8632,
              941.8017
            ],
            [
              844.08729,
              939.46515
            ],
            [
              843.8632,
              941.8017
            ]
          ]
        },
        "metadata": {
          "segment_id": 83355,
          "street_id": 614395972,
          "street_name": "Nguy\u1ec5n L\u01b0\u01a1ng B\u1eb1ng n\u1ed1i d\u00e0i",
          "street_type": "tertiary",
          "street_level": 4,
          "street_group": "614395972",
          "composite": true
        },
        "length_hint": 4.694542461454563,
        "speed_limit": 13.88888888888889
      },
      {
        "start": "5811875304",
        "end": "5811875304",
        "reverse": false,
        "shape": {
          "type": "polyline",
          "points": [
            [
              844.08729,
              939.46515
            ],
            [
              847.12621,
              908.08545
            ],
            [
              844.08729,
              939.46515
            ]
          ]
        },
        "metadata": {
          "segment_id": 83357,
          "street_id": 614395972,
          "street_name": "Nguy\u1ec5n L\u01b0\u01a1ng B\u1eb1ng n\u1ed1i d\u00e0i",
          "street_type": "tertiary",
          "street_level": 4,
          "street_group": "614395972",
          "composite": true
        },
        "length_hint": 63.053012833849486,
        "speed_limit": 13.88888888888889
      },
      {
        "start": "5168393222",
        "end": "5168393222",
        "reverse": false,
        "shape": {
          "type": "polyline",
          "points": [
            [
              880.07335,
              581.7954
            ],
            [
              876.85406,
              618.6141
            ],
            [
              880.07335,
              581.7954
            ]
          ]
        },
        "metadata": {
          "segment_id": 68774,
          "street_id": 532651474,
          "street_name": "Nguy\u1ec5n L\u01b0\u01a1ng B\u1eb1ng n\u1ed1i d\u00e0i",
          "street_type": "tertiary",
          "street_level": 4,
          "street_group": "532651474",
          "composite": true
        },
        "length_hint": 73.91834678330144,
        "speed_limit": 13.88888888888889
      },
      {
        "start": "5168393222",
        "end": "5168393222",
        "reverse": false,
        "shape": {
          "type": "polyline",
          "points": [
            [
              880.07335,
              581.7954
            ],
            [
              892.00494,
              471.46695
            ],
            [
              880.07335,
              581.7954
            ]
          ]
        },
        "metadata": {
          "segment_id": 68775,
          "street_id": 532651474,
          "street_name": "Nguy\u1ec5n L\u01b0\u01a1ng B\u1eb1ng n\u1ed1i d\u00e0i",
          "street_type": "tertiary",
          "street_level": 4,
          "street_group": "532651474",
          "composite": true
        },
        "length_hint": 221.94350379617418,
        "speed_limit": 13.88888888888889
      },
      {
        "start": "5168393219",
        "end": "5168393219",
        "reverse": false,
        "shape": {
          "type": "polyline",
          "points": [
            [
              866.97211,
              702.8076
            ],
            [
              855.9205,
              817.3707
            ],
            [
              866.97211,
              702.8076
            ]
          ]
        },
        "metadata": {
          "segment_id": 68768,
          "street_id": 532651474,
          "street_name": "Nguy\u1ec5n L\u01b0\u01a1ng B\u1eb1ng n\u1ed1i d\u00e0i",
          "street_type": "tertiary",
          "street_level": 4,
          "street_group": "532651474",
          "composite": true
        },
        "length_hint": 230.18985177632936,
        "speed_limit": 13.88888888888889
      },
      {
        "start": "5168393219",
        "end": "5168393219",
        "reverse": false,
        "shape": {
          "type": "polyline",
          "points": [
            [
              866.97211,
              702.8076
            ],
            [
              867.16887,
              699.9993
            ],
            [
              866.97211,
              702.8076
            ]
          ]
        },
        "metadata": {
          "segment_id": 68769,
          "street_id": 532651474,
          "street_name": "Nguy\u1ec5n L\u01b0\u01a1ng B\u1eb1ng n\u1ed1i d\u00e0i",
          "street_type": "tertiary",
          "street_level": 4,
          "street_group": "532651474",
          "composite": true
        },
        "length_hint": 5.630368864506178,
        "speed_limit": 13.88888888888889
      },
      {
        "start": "5168393220",
        "end": "5168393220",
        "reverse": false,
        "shape": {
          "type": "polyline",
          "points": [
            [
              867.16887,
              699.9993
            ],
            [
              876.85406,
              618.6141
            ],
            [
              867.16887,
              699.9993
            ]
          ]
        },
        "metadata": {
          "segment_id": 68771,
          "street_id": 532651474,
          "street_name": "Nguy\u1ec5n L\u01b0\u01a1ng B\u1eb1ng n\u1ed1i d\u00e0i",
          "street_type": "tertiary",
          "street_level": 4,
          "street_group": "532651474",
          "composite": true
        },
        "length_hint": 163.9189273314841,
        "speed_limit": 13.88888888888889
      },
      {
        "start": "2153156619",
        "end": "2153156619",
        "reverse": false,
        "shape": {
          "type": "polyline",
          "points": [
            [
              622.37186,
              434.32635
            ],
            [
              647.30631,
              440.9919
            ],
            [
              622.37186,
              434.32635
            ]
          ]
        },
        "metadata": {
          "segment_id": 11149,
          "street_id": 32584000,
          "street_name": "Ph\u1ea1m H\u1eefu L\u1ea7u",
          "street_type": "tertiary",
          "street_level": 4,
          "street_group": "32584000",
          "composite": true
        },
        "length_hint": 51.62000982584192,
        "speed_limit": 13.88888888888889
      },
      {
        "start": "2153156619",
        "end": "2153156619",
        "reverse": false,
        "shape": {
          "type": "polyline",
          "points": [
            [
              622.37186,
              434.32635
            ],
            [
              604.89807,
              428.84295
            ],
            [
              622.37186,
              434.32635
            ]
          ]
        },
        "metadata": {
          "segment_id": 11150,
          "street_id": 32584000,
          "street_name": "Ph\u1ea1m H\u1eefu L\u1ea7u",
          "street_type": "tertiary",
          "street_level": 4,
          "street_group": "32584000",
          "composite": true
        },
        "length_hint": 36.62791353730651,
        "speed_limit": 13.88888888888889
      },
      {
        "start": "366383786",
        "end": "366383786",
        "reverse": false,
        "shape": {
          "type": "polyline",
          "points": [
            [
              575.20848,
              419.31915
            ],
            [
              604.89807,
              428.84295
            ],
            [
              575.20848,
              419.31915
            ]
          ]
        },
        "metadata": {
          "segment_id": 11153,
          "street_id": 32584000,
          "street_name": "Ph\u1ea1m H\u1eefu L\u1ea7u",
          "street_type": "tertiary",
          "street_level": 4,
          "street_group": "32584000",
          "composite": true
        },
        "length_hint": 62.359426578765046,
        "speed_limit": 13.88888888888889
      },
      {
        "start": "2153156635",
        "end": "2153156635",
        "reverse": false,
        "shape": {
          "type": "polyline",
          "points": [
            [
              765.44158,
              456.6207
            ],
            [
              784.29272,
              458.66865
            ],
            [
              765.44158,
              456.6207
            ]
          ]
        },
        "metadata": {
          "segment_id": 11137,
          "street_id": 32584000,
          "street_name": "Ph\u1ea1m H\u1eefu L\u1ea7u",
          "street_type": "tertiary",
          "street_level": 4,
          "street_group": "32584000",
          "composite": true
        },
        "length_hint": 37.92411256718341,
        "speed_limit": 13.88888888888889
      },
      {
        "start": "2153156635",
        "end": "2153156635",
        "reverse": false,
        "shape": {
          "type": "polyline",
          "points": [
            [
              765.44158,
              456.6207
            ],
            [
              741.84076,
              454.767
            ],
            [
              765.44158,
              456.6207
            ]
          ]
        },
        "metadata": {
          "segment_id": 11138,
          "street_id": 32584000,
          "street_name": "Ph\u1ea1m H\u1eefu L\u1ea7u",
          "street_type": "tertiary",
          "street_level": 4,
          "street_group": "32584000",
          "composite": true
        },
        "length_hint": 47.34701293059151,
        "speed_limit": 13.88888888888889
      },
      {
        "start": "2159584348",
        "end": "2159584348",
        "reverse": false,
        "shape": {
          "type": "polyline",
          "points": [
            [
              860.69204,
              468.0204
            ],
            [
              878.94742,
              470.1738
            ],
            [
              860.69204,
              468.0204
            ]
          ]
        },
        "metadata": {
          "segment_id": 11129,
          "street_id": 32584000,
          "street_name": "Ph\u1ea1m H\u1eefu L\u1ea7u",
          "street_type": "tertiary",
          "street_level": 4,
          "street_group": "32584000",
          "composite": true
        },
        "length_hint": 36.763896991717196,
        "speed_limit": 13.88888888888889
      },
      {
        "start": "2159584348",
        "end": "2159584348",
        "reverse": false,
        "shape": {
          "type": "polyline",
          "points": [
            [
              860.69204,
              468.0204
            ],
            [
              832.74053,
              464.71815
            ],
            [
              860.69204,
              468.0204
            ]
          ]
        },
        "metadata": {
          "segment_id": 11130,
          "street_id": 32584000,
          "street_name": "Ph\u1ea1m H\u1eefu L\u1ea7u",
          "street_type": "tertiary",
          "street_level": 4,
          "street_group": "32584000",
          "composite": true
        },
        "length_hint": 56.29180282572585,
        "speed_limit": 13.88888888888889
      },
      {
        "start": "2153156644",
        "end": "2153156644",
        "reverse": false,
        "shape": {
          "type": "polyline",
          "points": [
            [
              892.00494,
              471.46695
            ],
            [
              886.85626,
              470.75655
            ],
            [
              892.00494,
              471.46695
            ]
          ]
        },
        "metadata": {
          "segment_id": 11124,
          "street_id": 32584000,
          "street_name": "Ph\u1ea1m H\u1eefu L\u1ea7u",
          "street_type": "tertiary",
          "street_level": 4,
          "street_group": "32584000",
          "composite": true
        },
        "length_hint": 10.394916815905768,
        "speed_limit": 13.88888888888889
      },
      {
        "start": "5811875312",
        "end": "5811875312",
        "reverse": false,
        "shape": {
          "type": "polyline",
          "points": [
            [
              886.85626,
              470.75655
            ],
            [
              878.94742,
              470.1738
            ],
            [
              886.85626,
              470.75655
            ]
          ]
        },
        "metadata": {
          "segment_id": 11126,
          "street_id": 32584000,
          "street_name": "Ph\u1ea1m H\u1eefu L\u1ea7u",
          "street_type": "tertiary",
          "street_level": 4,
          "street_group": "32584000",
          "composite": true
        },
        "length_hint": 15.860560861218097,
        "speed_limit": 13.88888888888889
      },
      {
        "start": "2159584309",
        "end": "2159584309",
        "reverse": false,
        "shape": {
          "type": "polyline",
          "points": [
            [
              832.74053,
              464.71815
            ],
            [
              816.85179,
              462.84225
            ],
            [
              832.74053,
              464.71815
            ]
          ]
        },
        "metadata": {
          "segment_id": 11132,
          "street_id": 32584000,
          "street_name": "Ph\u1ea1m H\u1eefu L\u1ea7u",
          "street_type": "tertiary",
          "street_level": 4,
          "street_group": "32584000",
          "composite": true
        },
        "length_hint": 31.998191173727275,
        "speed_limit": 13.88888888888889
      },
      {
        "start": "366416234",
        "end": "366416234",
        "reverse": false,
        "shape": {
          "type": "polyline",
          "points": [
            [
              816.85179,
              462.84225
            ],
            [
              784.29272,
              458.66865
            ],
            [
              816.85179,
              462.84225
            ]
          ]
        },
        "metadata": {
          "segment_id": 11134,
          "street_id": 32584000,
          "street_name": "Ph\u1ea1m H\u1eefu L\u1ea7u",
          "street_type": "tertiary",
          "street_level": 4,
          "street_group": "32584000",
          "composite": true
        },
        "length_hint": 65.65095509510584,
        "speed_limit": 13.88888888888889
      },
      {
        "start": "366426823",
        "end": "366426823",
        "reverse": false,
        "shape": {
          "type": "polyline",
          "points": [
            [
              710.21632,
              450.2604
            ],
            [
              741.84076,
              454.767
            ],
            [
              710.21632,
              450.2604
            ]
          ]
        },
        "metadata": {
          "segment_id": 11141,
          "street_id": 32584000,
          "street_name": "Ph\u1ea1m H\u1eefu L\u1ea7u",
          "street_type": "tertiary",
          "street_level": 4,
          "street_group": "32584000",
          "composite": true
        },
        "length_hint": 63.887859531325766,
        "speed_limit": 13.88888888888889
      },
      {
        "start": "366426823",
        "end": "366426823",
        "reverse": false,
        "shape": {
          "type": "polyline",
          "points": [
            [
              710.21632,
              450.2604
            ],
            [
              674.29585,
              444.7881
            ],
            [
              710.21632,
              450.2604
            ]
          ]
        },
        "metadata": {
          "segment_id": 11142,
          "street_id": 32584000,
          "street_name": "Ph\u1ea1m H\u1eefu L\u1ea7u",
          "street_type": "tertiary",
          "street_level": 4,
          "street_group": "32584000",
          "composite": true
        },
        "length_hint": 72.6698350709812,
        "speed_limit": 13.88888888888889
      },
      {
        "start": "714567039",
        "end": "714567039",
        "reverse": false,
        "shape": {
          "type": "polyline",
          "points": [
            [
              674.29585,
              444.7881
            ],
            [
              664.14061,
              443.9556
            ],
            [
              674.29585,
              444.7881
            ]
          ]
        },
        "metadata": {
          "segment_id": 11144,
          "street_id": 32584000,
          "street_name": "Ph\u1ea1m H\u1eefu L\u1ea7u",
          "street_type": "tertiary",
          "street_level": 4,
          "street_group": "32584000",
          "composite": true
        },
        "length_hint": 20.37861189655455,
        "speed_limit": 13.88888888888889
      },
      {
        "start": "366397697",
        "end": "366397697",
        "reverse": false,
        "shape": {
          "type": "polyline",
          "points": [
            [
              664.14061,
              443.9556
            ],
            [
              647.30631,
              440.9919
            ],
            [
              664.14061,
              443.9556
            ]
          ]
        },
        "metadata": {
          "segment_id": 11146,
          "street_id": 32584000,
          "street_name": "Ph\u1ea1m H\u1eefu L\u1ea7u",
          "street_type": "tertiary",
          "street_level": 4,
          "street_group": "32584000",
          "composite": true
        },
        "length_hint": 34.18638174361245,
        "speed_limit": 13.88888888888889
      },
      {
        "start": "366384660",
        "end": "366384660",
        "reverse": false,
        "shape": {
          "type": "polyline",
          "points": [
            [
              926.77215,
              475.92915
            ],
            [
              976.75035,
              481.8288
            ],
            [
              926.77215,
              475.92915
            ]
          ]
        },
        "metadata": {
          "segment_id": 83378,
          "street_id": 614403336,
          "street_name": "Ph\u1ea1m H\u1eefu L\u1ea7u",
          "street_type": "tertiary",
          "street_level": 4,
          "street_group": "614403336",
          "composite": true
        },
        "length_hint": 100.6504117301564,
        "speed_limit": 13.88888888888889
      },
      {
        "start": "366384660",
        "end": "366384660",
        "reverse": false,
        "shape": {
          "type": "polyline",
          "points": [
            [
              926.77215,
              475.92915
            ],
            [
              911.4573,
              474.06435
            ],
            [
              926.77215,
              475.92915
            ]
          ]
        },
        "metadata": {
          "segment_id": 83379,
          "street_id": 614403336,
          "street_name": "Ph\u1ea1m H\u1eefu L\u1ea7u",
          "street_type": "tertiary",
          "street_level": 4,
          "street_group": "614403336",
          "composite": true
        },
        "length_hint": 30.85593035787444,
        "speed_limit": 13.88888888888889
      },
      {
        "start": "2153156644",
        "end": "2153156644",
        "reverse": false,
        "shape": {
          "type": "polyline",
          "points": [
            [
              892.00494,
              471.46695
            ],
            [
              897.44876,
              472.3272
            ],
            [
              892.00494,
              471.46695
            ]
          ]
        },
        "metadata": {
          "segment_id": 83386,
          "street_id": 614403336,
          "street_name": "Ph\u1ea1m H\u1eefu L\u1ea7u",
          "street_type": "tertiary",
          "street_level": 4,
          "street_group": "614403336",
          "composite": true
        },
        "length_hint": 11.02274126610973,
        "speed_limit": 13.88888888888889
      },
      {
        "start": "2153156645",
        "end": "2153156645",
        "reverse": false,
        "shape": {
          "type": "polyline",
          "points": [
            [
              903.09481,
              473.04315
            ],
            [
              911.4573,
              474.06435
            ],
            [
              903.09481,
              473.04315
            ]
          ]
        },
        "metadata": {
          "segment_id": 83382,
          "street_id": 614403336,
          "street_name": "Ph\u1ea1m H\u1eefu L\u1ea7u",
          "street_type": "tertiary",
          "street_level": 4,
          "street_group": "614403336",
          "composite": true
        },
        "length_hint": 16.84922412933006,
        "speed_limit": 13.88888888888889
      },
      {
        "start": "2153156645",
        "end": "2153156645",
        "reverse": false,
        "shape": {
          "type": "polyline",
          "points": [
            [
              903.09481,
              473.04315
            ],
            [
              897.44876,
              472.3272
            ],
            [
              903.09481,
              473.04315
            ]
          ]
        },
        "metadata": {
          "segment_id": 83383,
          "street_id": 614403336,
          "street_name": "Ph\u1ea1m H\u1eefu L\u1ea7u",
          "street_type": "tertiary",
          "street_level": 4,
          "street_group": "614403336",
          "composite": true
        },
        "length_hint": 11.3825243254738,
        "speed_limit": 13.88888888888889
      },
      {
        "start": "5811677825",
        "end": "5811677825",
        "reverse": false,
        "shape": {
          "type": "polyline",
          "points": [
            [
              1004.12796,
              484.93125
            ],
            [
              1029.01868,
              487.75065
            ],
            [
              1004.12796,
              484.93125
            ]
          ]
        },
        "metadata": {
          "segment_id": 83374,
          "street_id": 614403336,
          "street_name": "Ph\u1ea1m H\u1eefu L\u1ea7u",
          "street_type": "tertiary",
          "street_level": 4,
          "street_group": "614403336",
          "composite": true
        },
        "length_hint": 50.09977878108421,
        "speed_limit": 13.88888888888889
      },
      {
        "start": "5811677825",
        "end": "5811677825",
        "reverse": false,
        "shape": {
          "type": "polyline",
          "points": [
            [
              1004.12796,
              484.93125
            ],
            [
              976.75035,
              481.8288
            ],
            [
              1004.12796,
              484.93125
            ]
          ]
        },
        "metadata": {
          "segment_id": 83375,
          "street_id": 614403336,
          "street_name": "Ph\u1ea1m H\u1eefu L\u1ea7u",
          "street_type": "tertiary",
          "street_level": 4,
          "street_group": "614403336",
          "composite": true
        },
        "length_hint": 55.105670318565224,
        "speed_limit": 13.88888888888889
      },
      {
        "start": "366381783",
        "end": "366381783",
        "reverse": false,
        "shape": {
          "type": "polyline",
          "points": [
            [
              1029.01868,
              487.75065
            ],
            [
              1085.65955,
              495.04335
            ],
            [
              1029.01868,
              487.75065
            ]
          ]
        },
        "metadata": {
          "segment_id": 83372,
          "street_id": 614403336,
          "street_name": "Ph\u1ea1m H\u1eefu L\u1ea7u",
          "street_type": "tertiary",
          "street_level": 4,
          "street_group": "614403336",
          "composite": true
        },
        "length_hint": 114.2168398730576,
        "speed_limit": 13.88888888888889
      },
      {
        "start": "1628403235",
        "end": "2351814884",
        "reverse": false,
        "shape": {
          "type": "polyline",
          "points": [
            [
              745.55742,
              1102.01355
            ],
            [
              770.59572,
              1061.55405
            ],
            [
              774.83162,
              1054.64985
            ]
          ]
        },
        "metadata": {
          "segment_id": 26131,
          "street_id": 149904637,
          "street_name": "Nguy\u1ec5n L\u01b0\u01a1ng B\u1eb1ng",
          "street_type": "secondary",
          "street_level": 3,
          "street_group": "149904637",
          "composite": true
        },
        "length_hint": 55.6803789580252,
        "speed_limit": 11.11111111111111
      },
      {
        "start": "1628403164",
        "end": "2346953828",
        "reverse": false,
        "shape": {
          "type": "polyline",
          "points": [
            [
              850.99045,
              949.09995
            ],
            [
              843.48607,
              950.45415
            ],
            [
              838.88943,
              954.2226
            ],
            [
              835.07438,
              958.33515
            ],
            [
              832.31421,
              961.94265
            ]
          ]
        },
        "metadata": {
          "segment_id": 31935,
          "street_id": 205957966,
          "street_name": "Nguy\u1ec5n L\u01b0\u01a1ng B\u1eb1ng",
          "street_type": "secondary",
          "street_level": 3,
          "street_group": "205957966",
          "composite": true
        },
        "length_hint": 23.721435007983096,
        "speed_limit": 11.11111111111111
      },
      {
        "start": "2351814879",
        "end": "2244906852",
        "reverse": false,
        "shape": {
          "type": "polyline",
          "points": [
            [
              778.81611,
              1057.1085
            ],
            [
              774.0555,
              1064.81745
            ],
            [
              768.8303,
              1073.9361
            ]
          ]
        },
        "metadata": {
          "segment_id": 34516,
          "street_id": 215071573,
          "street_name": "Nguy\u1ec5n L\u01b0\u01a1ng B\u1eb1ng",
          "street_type": "secondary",
          "street_level": 3,
          "street_group": "215071573",
          "composite": true
        },
        "length_hint": 19.570064004013414,
        "speed_limit": 11.11111111111111
      },
      {
        "start": "714567061",
        "end": "714567046",
        "reverse": false,
        "shape": {
          "type": "polyline",
          "points": [
            [
              0.0,
              185.6142
            ],
            [
              24.43707,
              150.24405
            ],
            [
              43.40845,
              115.0293
            ],
            [
              52.43776,
              96.99735
            ],
            [
              60.50511,
              79.73685
            ],
            [
              77.04427,
              42.51855
            ],
            [
              89.48963,
              0.0
            ]
          ]
        },
        "metadata": {
          "segment_id": 22213,
          "street_id": 57559372,
          "street_name": "Nguy\u1ec5n H\u1eefu Th\u1ecd",
          "street_type": "secondary",
          "street_level": 3,
          "street_group": "57559372",
          "composite": true
        },
        "length_hint": 207.24007644515234,
        "speed_limit": 11.11111111111111
      },
      {
        "start": "714567126",
        "end": "714567051",
        "reverse": false,
        "shape": {
          "type": "polyline",
          "points": [
            [
              128.28505,
              11.1111
            ],
            [
              124.38255,
              3.7962
            ],
            [
              121.4912,
              1.88145
            ],
            [
              117.73628,
              1.8648
            ],
            [
              114.27104,
              3.3855
            ],
            [
              111.47261,
              5.6166
            ]
          ]
        },
        "metadata": {
          "segment_id": 83217,
          "street_id": 614336152,
          "street_name": "Nguy\u1ec5n H\u1eefu Th\u1ecd",
          "street_type": "secondary_link",
          "street_level": 3,
          "street_group": "614336152",
          "composite": true
        },
        "length_hint": 22.876829768146074,
        "speed_limit": 11.11111111111111
      },
      {
        "start": "2346953828",
        "end": "5811493713",
        "reverse": false,
        "shape": {
          "type": "polyline",
          "points": [
            [
              832.31421,
              961.94265
            ],
            [
              832.06279,
              968.78025
            ],
            [
              830.48867,
              972.7152
            ],
            [
              821.08223,
              990.72495
            ],
            [
              814.79123,
              1001.82495
            ]
          ]
        },
        "metadata": {
          "segment_id": 34512,
          "street_id": 215071572,
          "street_name": "C\u1ea7u \u00d4ng \u0110\u1ed9i",
          "street_type": "tertiary",
          "street_level": 4,
          "street_group": "215071572",
          "composite": true
        },
        "length_hint": 44.15740482755389,
        "speed_limit": 13.88888888888889
      },
      {
        "start": "2346953828",
        "end": "5811493714",
        "reverse": false,
        "shape": {
          "type": "polyline",
          "points": [
            [
              832.31421,
              961.94265
            ],
            [
              827.82142,
              969.54615
            ],
            [
              826.01228,
              972.19905
            ],
            [
              810.80128,
              999.7659
            ]
          ]
        },
        "metadata": {
          "segment_id": 83265,
          "street_id": 614356091,
          "street_name": "C\u1ea7u \u00d4ng \u0110\u1ed9i",
          "street_type": "secondary",
          "street_level": 3,
          "street_group": "614356091",
          "composite": true
        },
        "length_hint": 43.52773071552935,
        "speed_limit": 11.11111111111111
      },
      {
        "start": "5811493715",
        "end": "5811875294",
        "reverse": false,
        "shape": {
          "type": "polyline",
          "points": [
            [
              804.09489,
              997.9677
            ],
            [
              811.81243,
              985.57455
            ],
            [
              822.27922,
              966.42705
            ],
            [
              824.21407,
              964.62885
            ],
            [
              827.70664,
              962.0148
            ]
          ]
        },
        "metadata": {
          "segment_id": 38166,
          "street_id": 225367281,
          "street_name": "C\u1ea7u \u00d4ng \u0110\u1ed9i",
          "street_type": "tertiary",
          "street_level": 4,
          "street_group": "225367281",
          "composite": true
        },
        "length_hint": 43.42515805061889,
        "speed_limit": 13.88888888888889
      },
      {
        "start": "5811821180",
        "end": "5811821180",
        "reverse": false,
        "shape": {
          "type": "polyline",
          "points": [
            [
              848.61288,
              892.70085
            ],
            [
              847.12621,
              908.08545
            ],
            [
              848.61288,
              892.70085
            ]
          ]
        },
        "metadata": {
          "segment_id": 83348,
          "street_id": 614395968,
          "street_name": "Nguy\u1ec5n L\u01b0\u01a1ng B\u1eb1ng n\u1ed1i d\u00e0i",
          "street_type": "tertiary",
          "street_level": 4,
          "street_group": "614395968",
          "composite": true
        },
        "length_hint": 30.912528518314566,
        "speed_limit": 13.88888888888889
      },
      {
        "start": "5811763199",
        "end": "5811763199",
        "reverse": false,
        "shape": {
          "type": "polyline",
          "points": [
            [
              849.0228,
              888.5106
            ],
            [
              848.61288,
              892.70085
            ],
            [
              849.0228,
              888.5106
            ]
          ]
        },
        "metadata": {
          "segment_id": 83344,
          "street_id": 614395966,
          "street_name": "Nguy\u1ec5n L\u01b0\u01a1ng B\u1eb1ng n\u1ed1i d\u00e0i",
          "street_type": "tertiary",
          "street_level": 4,
          "street_group": "614395966",
          "composite": true
        },
        "length_hint": 8.420505796898398,
        "speed_limit": 13.88888888888889
      },
      {
        "start": "5811763199",
        "end": "5811763199",
        "reverse": false,
        "shape": {
          "type": "polyline",
          "points": [
            [
              849.0228,
              888.5106
            ],
            [
              854.13322,
              835.6191
            ],
            [
              849.0228,
              888.5106
            ]
          ]
        },
        "metadata": {
          "segment_id": 83345,
          "street_id": 614395966,
          "street_name": "Nguy\u1ec5n L\u01b0\u01a1ng B\u1eb1ng n\u1ed1i d\u00e0i",
          "street_type": "tertiary",
          "street_level": 4,
          "street_group": "614395966",
          "composite": true
        },
        "length_hint": 106.27562589467814,
        "speed_limit": 13.88888888888889
      },
      {
        "start": "5811821182",
        "end": "5811821182",
        "reverse": false,
        "shape": {
          "type": "polyline",
          "points": [
            [
              854.13322,
              835.6191
            ],
            [
              855.9205,
              817.3707
            ],
            [
              854.13322,
              835.6191
            ]
          ]
        },
        "metadata": {
          "segment_id": 83349,
          "street_id": 614395970,
          "street_name": "Nguy\u1ec5n L\u01b0\u01a1ng B\u1eb1ng n\u1ed1i d\u00e0i",
          "street_type": "tertiary",
          "street_level": 4,
          "street_group": "614395970",
          "composite": true
        },
        "length_hint": 36.67143151601245,
        "speed_limit": 13.88888888888889
      },
      {
        "start": "366475621",
        "end": "366475621",
        "reverse": false,
        "shape": {
          "type": "polyline",
          "points": [
            [
              476.70594,
              376.4343
            ],
            [
              575.20848,
              419.31915
            ],
            [
              476.70594,
              376.4343
            ]
          ]
        },
        "metadata": {
          "segment_id": 20004,
          "street_id": 33569361,
          "street_name": "C\u1ea7u Ph\u01b0\u1edbc Long",
          "street_type": "tertiary",
          "street_level": 4,
          "street_group": "33569361",
          "composite": true
        },
        "length_hint": 214.86610478131817,
        "speed_limit": 13.88888888888889
      },
      {
        "start": "5811875291",
        "end": "5811875290",
        "reverse": false,
        "shape": {
          "type": "polyline",
          "points": [
            [
              789.52338,
              1029.5361
            ],
            [
              807.7405,
              998.889
            ]
          ]
        },
        "metadata": {
          "segment_id": 83359,
          "street_id": 614403334,
          "street_name": "C\u1ea7u 15B",
          "street_type": "secondary",
          "street_level": 3,
          "street_group": "614403334",
          "composite": true
        },
        "length_hint": 35.65260438599686,
        "speed_limit": 11.11111111111111
      },
      {
        "start": "5811875290",
        "end": "5811875296",
        "reverse": false,
        "shape": {
          "type": "polyline",
          "points": [
            [
              807.7405,
              998.889
            ],
            [
              824.9574,
              967.3206
            ],
            [
              827.70664,
              962.0148
            ],
            [
              831.06257,
              956.3316
            ],
            [
              834.91041,
              951.2589
            ],
            [
              838.65987,
              948.5172
            ],
            [
              843.42595,
              946.0863
            ]
          ]
        },
        "metadata": {
          "segment_id": 31608,
          "street_id": 205341811,
          "street_name": "C\u1ea7u 15B",
          "street_type": "secondary",
          "street_level": 3,
          "street_group": "205341811",
          "composite": true
        },
        "length_hint": 64.89605844338942,
        "speed_limit": 11.11111111111111
      },
      {
        "start": "5811875296",
        "end": "1628403185",
        "reverse": false,
        "shape": {
          "type": "polyline",
          "points": [
            [
              843.42595,
              946.0863
            ],
            [
              851.39491,
              944.60445
            ],
            [
              853.94739,
              944.5434
            ],
            [
              858.18329,
              945.4869
            ],
            [
              887.7745,
              952.89615
            ],
            [
              1043.95092,
              989.7426
            ],
            [
              1083.42409,
              998.7447
            ]
          ]
        },
        "metadata": {
          "segment_id": 26104,
          "street_id": 149904634,
          "street_name": "Ho\u00e0ng Qu\u1ed1c Vi\u1ec7t",
          "street_type": "secondary",
          "street_level": 3,
          "street_group": "149904634",
          "composite": true
        },
        "length_hint": 246.45395629472497,
        "speed_limit": 11.11111111111111
      },
      {
        "start": "2351814884",
        "end": "5811875291",
        "reverse": false,
        "shape": {
          "type": "polyline",
          "points": [
            [
              774.83162,
              1054.64985
            ],
            [
              789.52338,
              1029.5361
            ]
          ]
        },
        "metadata": {
          "segment_id": 83360,
          "street_id": 614403335,
          "street_name": "C\u1ea7u 15B",
          "street_type": "secondary",
          "street_level": 3,
          "street_group": "614403335",
          "composite": true
        },
        "length_hint": 29.095502246225223,
        "speed_limit": 11.11111111111111
      },
      {
        "start": "5811493712",
        "end": "2351814879",
        "reverse": false,
        "shape": {
          "type": "polyline",
          "points": [
            [
              782.85525,
              1048.0842
            ],
            [
              778.81611,
              1057.1085
            ]
          ]
        },
        "metadata": {
          "segment_id": 38555,
          "street_id": 226335440,
          "street_name": "C\u1ea7u 15B",
          "street_type": "secondary",
          "street_level": 3,
          "street_group": "226335440",
          "composite": true
        },
        "length_hint": 9.886993599148353,
        "speed_limit": 11.11111111111111
      },
      {
        "start": "5811493713",
        "end": "5811493718",
        "reverse": false,
        "shape": {
          "type": "polyline",
          "points": [
            [
              814.79123,
              1001.82495
            ],
            [
              795.99475,
              1034.25915
            ]
          ]
        },
        "metadata": {
          "segment_id": 83270,
          "street_id": 614356098,
          "street_name": "C\u1ea7u \u00d4ng \u0110\u1ed9i",
          "street_type": "tertiary",
          "street_level": 4,
          "street_group": "614356098",
          "composite": true
        },
        "length_hint": 37.48713099225403,
        "speed_limit": 13.88888888888889
      },
      {
        "start": "5811493714",
        "end": "5811493717",
        "reverse": false,
        "shape": {
          "type": "polyline",
          "points": [
            [
              810.80128,
              999.7659
            ],
            [
              791.74245,
              1031.5452
            ]
          ]
        },
        "metadata": {
          "segment_id": 83268,
          "street_id": 614356093,
          "street_name": "C\u1ea7u \u00d4ng \u0110\u1ed9i",
          "street_type": "secondary",
          "street_level": 3,
          "street_group": "614356093",
          "composite": true
        },
        "length_hint": 37.05621283211365,
        "speed_limit": 11.11111111111111
      },
      {
        "start": "5811493716",
        "end": "5811493715",
        "reverse": false,
        "shape": {
          "type": "polyline",
          "points": [
            [
              786.01988,
              1026.97755
            ],
            [
              804.09489,
              997.9677
            ]
          ]
        },
        "metadata": {
          "segment_id": 83263,
          "street_id": 614356087,
          "street_name": "C\u1ea7u \u00d4ng \u0110\u1ed9i",
          "street_type": "tertiary",
          "street_level": 4,
          "street_group": "614356087",
          "composite": true
        },
        "length_hint": 34.18007290107209,
        "speed_limit": 13.88888888888889
      },
      {
        "start": "5811493717",
        "end": "5811493712",
        "reverse": false,
        "shape": {
          "type": "polyline",
          "points": [
            [
              791.74245,
              1031.5452
            ],
            [
              782.85525,
              1048.0842
            ]
          ]
        },
        "metadata": {
          "segment_id": 38556,
          "street_id": 226335441,
          "street_name": "C\u1ea7u \u00d4ng \u0110\u1ed9i",
          "street_type": "secondary",
          "street_level": 3,
          "street_group": "226335441",
          "composite": true
        },
        "length_hint": 18.775538470041273,
        "speed_limit": 11.11111111111111
      },
      {
        "start": "5811493718",
        "end": "5811493720",
        "reverse": false,
        "shape": {
          "type": "polyline",
          "points": [
            [
              795.99475,
              1034.25915
            ],
            [
              781.63093,
              1059.1731
            ]
          ]
        },
        "metadata": {
          "segment_id": 83269,
          "street_id": 614356096,
          "street_name": "C\u1ea7u \u00d4ng \u0110\u1ed9i",
          "street_type": "tertiary",
          "street_level": 4,
          "street_group": "614356096",
          "composite": true
        },
        "length_hint": 28.758028958795006,
        "speed_limit": 13.88888888888889
      },
      {
        "start": "5811493720",
        "end": "5811493721",
        "reverse": false,
        "shape": {
          "type": "polyline",
          "points": [
            [
              781.63093,
              1059.1731
            ],
            [
              771.61234,
              1075.1016
            ]
          ]
        },
        "metadata": {
          "segment_id": 83274,
          "street_id": 614356102,
          "street_name": "\u0110\u01b0\u1eddng Nguy\u1ec5n L\u01b0\u01a1ng B\u1eb1ng",
          "street_type": "tertiary",
          "street_level": 4,
          "street_group": "614356102",
          "composite": true
        },
        "length_hint": 18.817259573011686,
        "speed_limit": 13.88888888888889
      },
      {
        "start": "5811493722",
        "end": "5811493716",
        "reverse": false,
        "shape": {
          "type": "polyline",
          "points": [
            [
              770.80888,
              1051.39755
            ],
            [
              786.01988,
              1026.97755
            ]
          ]
        },
        "metadata": {
          "segment_id": 83264,
          "street_id": 614356089,
          "street_name": "C\u1ea7u \u00d4ng \u0110\u1ed9i",
          "street_type": "tertiary",
          "street_level": 4,
          "street_group": "614356089",
          "composite": true
        },
        "length_hint": 28.76996560651384,
        "speed_limit": 13.88888888888889
      },
      {
        "start": "5811493723",
        "end": "5811493722",
        "reverse": false,
        "shape": {
          "type": "polyline",
          "points": [
            [
              741.31605,
              1098.96105
            ],
            [
              770.80888,
              1051.39755
            ]
          ]
        },
        "metadata": {
          "segment_id": 83273,
          "street_id": 614356100,
          "street_name": "Ph\u01b0\u1eddng T\u00e2n Ph\u00fa",
          "street_type": "tertiary",
          "street_level": 4,
          "street_group": "614356100",
          "composite": true
        },
        "length_hint": 55.96528882851316,
        "speed_limit": 13.88888888888889
      },
      {
        "start": "714567051",
        "end": "5811478618",
        "reverse": false,
        "shape": {
          "type": "polyline",
          "points": [
            [
              111.47261,
              5.6166
            ],
            [
              102.90788,
              33.70515
            ],
            [
              97.01587,
              50.2164
            ],
            [
              91.42995,
              64.0026
            ],
            [
              61.02435,
              127.78875
            ],
            [
              39.8339,
              165.3123
            ],
            [
              15.927,
              199.5003
            ],
            [
              8.49367,
              209.8011
            ]
          ]
        },
        "metadata": {
          "segment_id": 22263,
          "street_id": 57559402,
          "street_name": "Nguy\u1ec5n H\u1eefu Th\u1ecd",
          "street_type": "secondary",
          "street_level": 3,
          "street_group": "57559402",
          "composite": true
        },
        "length_hint": 229.94753206035392,
        "speed_limit": 11.11111111111111
      },
      {
        "start": "2153156495",
        "end": "2153156495",
        "reverse": false,
        "shape": {
          "type": "polyline",
          "points": [
            [
              77.04427,
              42.51855
            ],
            [
              97.01587,
              50.2164
            ],
            [
              77.04427,
              42.51855
            ]
          ]
        },
        "metadata": {
          "segment_id": 31683,
          "street_id": 205341876,
          "street_name": "Nguy\u1ec5n H\u1eefu Th\u1ecd",
          "street_type": "secondary_link",
          "street_level": 3,
          "street_group": "205341876",
          "composite": true
        },
        "length_hint": 42.80755546314227,
        "speed_limit": 11.11111111111111
      },
      {
        "start": "1628403184",
        "end": "1628403164",
        "reverse": false,
        "shape": {
          "type": "polyline",
          "points": [
            [
              1042.60637,
              994.87635
            ],
            [
              996.21365,
              983.69865
            ],
            [
              886.70869,
              958.04655
            ],
            [
              856.15552,
              949.26645
            ],
            [
              850.99045,
              949.09995
            ]
          ]
        },
        "metadata": {
          "segment_id": 26100,
          "street_id": 149904633,
          "street_name": "Ho\u00e0ng Qu\u1ed1c Vi\u1ec7t",
          "street_type": "secondary",
          "street_level": 3,
          "street_group": "149904633",
          "composite": true
        },
        "length_hint": 197.1471596877155,
        "speed_limit": 11.11111111111111
      }
    ]
  }
}